odman/__init__.py
odman/cli/__init__.py
odman/cli/main.py
odman/core/__init__.py
odman/core/auth.py
odman/core/client.py
odman/core/config.py
odman/core/stats.py
odman/models/__init__.py
odman/models/file.py
odman/services/__init__.py
odman/services/download.py
odman/services/upload.py
odman/utils/__init__.py
odman/utils/helpers.py
odman/utils/progress.py
odman-0.3.0a0.dist-info/METADATA
odman-0.3.0a0.dist-info/WHEEL
odman-0.3.0a0.dist-info/entry_points.txt
odman-0.3.0a0.dist-info/licenses/LICENSE
odman-0.3.0a0.dist-info/RECORD
