Metadata-Version: 2.4
Name: odman
Version: 0.3.0a0
Summary: OneDrive Manager (odman) - A professional CLI tool for OneDrive file operations via app-only authentication.
License-File: LICENSE
Requires-Python: >=3.11
Requires-Dist: msal>=1.32.3
Requires-Dist: requests>=2.32.4
Requires-Dist: rich>=14.0.0
